[
  {
    "full_name": "ExamProCo/aws-bootcamp-cruddur-2023",
    "stargazers_count": 338,
    "open_issues_count": 8,
    "forks_count": 221
  },
  {
    "full_name": "donnemartin/system-design-primer",
    "stargazers_count": 222949,
    "open_issues_count": 383,
    "forks_count": 39475
  },
  {
    "full_name": "Ebazhanov/linkedin-skill-assessments-quizzes",
    "stargazers_count": 25393,
    "open_issues_count": 75,
    "forks_count": 13244
  },
  {
    "full_name": "curtisbarnard/leetcode-grind75-javascript",
    "stargazers_count": 20,
    "open_issues_count": 0,
    "forks_count": 2
  },
  {
    "full_name": "curtisbarnard/BANKI",
    "stargazers_count": 547,
    "open_issues_count": 6,
    "forks_count": 306
  },
  {
    "full_name": "swapagarwal/geeksay",
    "stargazers_count": 201,
    "open_issues_count": 200,
    "forks_count": 312
  },
  {
    "full_name": "sahat/hackathon-starter",
    "stargazers_count": 34149,
    "open_issues_count": 14,
    "forks_count": 8116
  },
  {
    "full_name": "firstcontributions/first-contributions",
    "stargazers_count": 34479,
    "open_issues_count": 233,
    "forks_count": 61405
  }
]